<?xml version="1.0" encoding="utf-8" ?>
<dwsync>
<file name="Comfortaa_400-Comfortaa_700.font.js" server="ftp.gratisperte.it" local="128954515660000000" remote="128960393400000000" />
<file name="Comfortaa_400.font.js" server="ftp.gratisperte.it" local="128933715920000000" remote="128960393400000000" />
<file name="cufon-yui.js" server="ftp.gratisperte.it" local="128933706440000000" remote="128960393400000000" />
<file name="jquery-1.3.2.js" server="ftp.gratisperte.it" local="128905802440000000" remote="128960393400000000" />
<file name="jquery.cycle.js" server="ftp.gratisperte.it" local="128905800680000000" remote="128960394000000000" />
<file name="jquery.functions.js" server="ftp.gratisperte.it" local="128905820140000000" remote="128960394000000000" />
<file name="Comfortaa_400-Comfortaa_700.font.js" server="ftp.iosmanetto.it" local="128954515660000000" remote="128964553800000000" />
<file name="Comfortaa_400.font.js" server="ftp.iosmanetto.it" local="128933715920000000" remote="128964553800000000" />
<file name="cufon-yui.js" server="ftp.iosmanetto.it" local="128933706440000000" remote="128964553800000000" />
<file name="jquery-1.3.2.js" server="ftp.iosmanetto.it" local="128905802440000000" remote="128964553800000000" />
<file name="jquery.cycle.js" server="ftp.iosmanetto.it" local="128905800680000000" remote="128964553800000000" />
<file name="jquery.functions.js" server="ftp.iosmanetto.it" local="128905820140000000" remote="128964553800000000" />
</dwsync>